pinenut/README.md
pinenut/__init__.py
pinenut/core/__init__.py
pinenut/core/activation.py
pinenut/core/backward.py
pinenut/core/computational_graph.py
pinenut/core/cuda.py
pinenut/core/dataset.py
pinenut/core/datasets.py
pinenut/core/dropout.py
pinenut/core/gradient_check.py
pinenut/core/layer.py
pinenut/core/loss.py
pinenut/core/math_base.py
pinenut/core/optimizer.py
pinenut/core/tensor.py
pinenut/core/utils.py
pinenut/examples/__init__.py
pinenut/examples/mnist/mnist_weights.npz
pinenut/examples/mnist/test_mnist.py
pinenut/examples/mnist/train_mnist.py
pinenut/examples/nn/test_concat.py
pinenut/examples/nn/test_dropout.py
pinenut/examples/nn/test_embedding.py
pinenut/examples/nn/test_linear.py
pinenut/examples/nn/test_linear2.py
pinenut/examples/nn/test_linear_pack.py
pinenut/examples/nn/test_spiral.py
pinenut/test/test_autograd.py
pinenut/test/test_basic_ops.py
pinenut/test/test_complex_math.py
pinenut/test/test_computational_graph.py
pinenut/test/test_gpu.py
pinenut/test/test_if_memory_leak.png
pinenut/test/test_if_memory_leak.png.dot
pinenut/test/test_if_memory_leak.py
pinenut/test/test_memory.png
pinenut/test/test_memory.png.dot
pinenut/test/test_memory_ndarray.py
pinenut-0.1.3.dist-info/LICENSE
pinenut-0.1.3.dist-info/METADATA
pinenut-0.1.3.dist-info/WHEEL
pinenut-0.1.3.dist-info/RECORD
